Metadata-Version: 1.1
Name: cassandra-backups
Version: 0.1
Summary: cassandra_backups is a tool to backup a Cassandra cluster to Amazon S3.
Home-page: http://github.com/jalvz/cassandra_backups
Author: Juan Alvarez
Author-email: juan@opbeat.com
License: UNKNOWN
Keywords: cassandra,AWS,S3,backup
Platform: UNKNOWN
Classifier: Intended Audience :: Developers
Classifier: Intended Audience :: System Administrators
Classifier: Operating System :: OS Independent
Classifier: Topic :: Software Development
Classifier: License :: OSI Approved :: GNU General Public License (GPL)
Classifier: Natural Language :: English
Classifier: Programming Language :: Python
Classifier: Topic :: Software Development :: Libraries :: Python Modules
